physrisk-0.20.0.dist-info/METADATA
physrisk-0.20.0.dist-info/WHEEL
physrisk-0.20.0.dist-info/licenses/LICENSE.txt
physrisk/__init__.py
physrisk/api/__init__.py
physrisk/api/v1/__init__.py
physrisk/api/v1/common.py
physrisk/api/v1/example_portfolios.py
physrisk/api/v1/exposure_req_resp.py
physrisk/api/v1/hazard_data.py
physrisk/api/v1/hazard_image.py
physrisk/api/v1/impact_req_resp.py
physrisk/api/v2/__init__.py
physrisk/container.py
physrisk/data/__init__.py
physrisk/data/colormap_provider.py
physrisk/data/geotiff_reader.py
physrisk/data/hazard_data_provider.py
physrisk/data/image_creator.py
physrisk/data/inventory.py
physrisk/data/inventory_reader.py
physrisk/data/pregenerated_hazard_model.py
physrisk/data/static/__init__.py
physrisk/data/static/example_portfolios/__init__.py
physrisk/data/static/example_portfolios/industrial_activity_small.json
physrisk/data/static/example_portfolios/mixed_small.json
physrisk/data/static/example_portfolios/power_generating_small.json
physrisk/data/static/example_portfolios/real_estate_small.json
physrisk/data/static/hazard/__init__.py
physrisk/data/static/hazard/inventory.json
physrisk/data/static/vulnerability/EU JRC global flood depth-damage functions.json
physrisk/data/static/vulnerability/__init__.py
physrisk/data/static/world.json
physrisk/data/static/world.py
physrisk/data/zarr_reader.py
physrisk/hazard_models/__init__.py
physrisk/hazard_models/core_hazards.py
physrisk/kernel/__init__.py
physrisk/kernel/__pycache__/events.sample_from_cumulative_probs-42.py310.1.nbc
physrisk/kernel/__pycache__/events.sample_from_cumulative_probs-42.py310.nbi
physrisk/kernel/assets.py
physrisk/kernel/calculation.py
physrisk/kernel/curve.py
physrisk/kernel/events.py
physrisk/kernel/exposure.py
physrisk/kernel/financial_model.py
physrisk/kernel/hazard_event_distrib.py
physrisk/kernel/hazard_model.py
physrisk/kernel/hazards.py
physrisk/kernel/impact.py
physrisk/kernel/impact_distrib.py
physrisk/kernel/risk.py
physrisk/kernel/vulnerability_distrib.py
physrisk/kernel/vulnerability_matrix_provider.py
physrisk/kernel/vulnerability_model.py
physrisk/requests.py
physrisk-0.20.0.dist-info/RECORD
