Metadata-Version: 2.1
Name: physrisk
Version: 0.20.0
Summary: Physical climate risk calculation engine.
Keywords: Climate Physical Risk
Author-Email: Joe Moorhouse <72577720+MichaelTiemannOSC@users.noreply.github.com>, Joseph Moorhouse <72577720+MichaelTiemannOSC@users.noreply.github.com>
License: Apache-2.0
Classifier: Intended Audience :: Developers
Classifier: Intended Audience :: Science/Research
Classifier: License :: OSI Approved :: Apache Software License
Classifier: Operating System :: MacOS
Classifier: Operating System :: Microsoft :: Windows
Classifier: Operating System :: Unix
Classifier: Programming Language :: Python
Classifier: Programming Language :: Python :: 3
Classifier: Programming Language :: Python :: 3 :: Only
Classifier: Programming Language :: Python :: 3.11
Classifier: Programming Language :: Python :: 3.10
Classifier: Programming Language :: Python :: 3.9
Classifier: Topic :: Office/Business :: Financial
Classifier: Topic :: Scientific/Engineering
Classifier: Topic :: Software Development
Project-URL: Homepage, https://github.com/is-climate/physrisk
Project-URL: Repository, https://github.com/os-climate/physrisk
Project-URL: Downloads, https://github.com/os-climate/physrisk/releases
Project-URL: Bug tracker, https://github.com/os-climate/physrisk/issues
Project-URL: Documentation, https://github.com/os-climate/physrisk/tree/main/docs
Project-URL: Source code, https://github.com/os-climate/physrisk
Requires-Python: <3.11,>=3.9
Requires-Dist: affine==2.3.0
Requires-Dist: dependency-injector==4.41.0
Requires-Dist: numba==0.56.4
Requires-Dist: numpy==1.22.0
Requires-Dist: pillow>=10.0.1
Requires-Dist: pydantic==2.4.2
Requires-Dist: python-dotenv==0.19.2
Requires-Dist: requests>=2.31.0
Requires-Dist: scipy>=1.10.0
Requires-Dist: s3fs==2022.1.0
Requires-Dist: zarr==2.10.3
